LICENSE
README.md
pyproject.toml
setup.py
PygroupBot.egg-info/PKG-INFO
PygroupBot.egg-info/SOURCES.txt
PygroupBot.egg-info/dependency_links.txt
PygroupBot.egg-info/requires.txt
PygroupBot.egg-info/top_level.txt
pygroupbot/__init__.py