Metadata-Version: 2.1
Name: PygroupBot
Version: 1.2.5
Summary: pygroupbot is python library that can you help to create your own simple telegram group manage bot
Home-page: https://github.com/ranujasanmir/pygroupbot
Author: PixCap TM
License: MIT
Keywords: telegram,bot
Classifier: Environment :: Console
Classifier: Intended Audience :: Developers
Classifier: License :: OSI Approved :: MIT License
Classifier: Topic :: Software Development :: Libraries :: Python Modules
Classifier: Natural Language :: English
Classifier: Operating System :: OS Independent
Classifier: Operating System :: POSIX
Classifier: Operating System :: Microsoft :: Windows
Classifier: Programming Language :: Python :: 3
Classifier: Programming Language :: Python :: 3.2
Classifier: Programming Language :: Python :: 3.5
License-File: LICENSE
